mlba/__init__.py
mlba/data.py
mlba/featureSelection.py
mlba/graphs.py
mlba/metric.py
mlba/textMining.py
mlba/version.py
mlba/csvFiles/Airfares.csv.gz
mlba/csvFiles/Amtrak.csv.gz
mlba/csvFiles/ApplianceShipments.csv.gz
mlba/csvFiles/AustralianWines.csv.gz
mlba/csvFiles/AutoAndElectronics.zip
mlba/csvFiles/Bank-bias-data.csv.gz
mlba/csvFiles/Bankruptcy.csv.gz
mlba/csvFiles/BareggTunnel.csv.gz
mlba/csvFiles/BathSoapHousehold.csv.gz
mlba/csvFiles/BostonHousing.csv.gz
mlba/csvFiles/COMPAS-clean.csv.gz
mlba/csvFiles/CanadianWorkHours.csv.gz
mlba/csvFiles/CatalogCrossSell.csv.gz
mlba/csvFiles/Cereals.csv.gz
mlba/csvFiles/CharlesBookClub.csv.gz
mlba/csvFiles/Cosmetics.csv.gz
mlba/csvFiles/CourseTopics.csv.gz
mlba/csvFiles/DepartmentStoreSales.csv.gz
mlba/csvFiles/EastWestAirlinesCluster.csv.gz
mlba/csvFiles/EastWestAirlinesNN.csv.gz
mlba/csvFiles/EbayTreemap.csv.gz
mlba/csvFiles/EmailABtest.csv.gz
mlba/csvFiles/Faceplate.csv.gz
mlba/csvFiles/FlightDelays.csv.gz
mlba/csvFiles/Fundraising.csv.gz
mlba/csvFiles/FutureFundraising.csv.gz
mlba/csvFiles/GermanCredit.csv.gz
mlba/csvFiles/Hair-Care-Product.csv.gz
mlba/csvFiles/IMDB-Dataset-10K.csv.gz
mlba/csvFiles/LaptopSales.csv.gz
mlba/csvFiles/LaptopSalesJanuary2008.csv.gz
mlba/csvFiles/MovieLensMovies.csv.gz
mlba/csvFiles/MovieLensRatings.csv.gz
mlba/csvFiles/NYPD_Motor_Vehicle_Collisions_1000.csv.gz
mlba/csvFiles/NaturalGasSales.csv.gz
mlba/csvFiles/Pharmaceuticals.csv.gz
mlba/csvFiles/RidingMowers.csv.gz
mlba/csvFiles/SC-US-students-GPS-data-2016.csv.gz
mlba/csvFiles/SP500.csv.gz
mlba/csvFiles/Sept11Travel.csv.gz
mlba/csvFiles/ShampooSales.csv.gz
mlba/csvFiles/SouvenirSales.csv.gz
mlba/csvFiles/Spambase.csv.gz
mlba/csvFiles/SystemAdministrators.csv.gz
mlba/csvFiles/Taxi-cancellation-case.csv.gz
mlba/csvFiles/Tayko.csv.gz
mlba/csvFiles/TinyData.csv.gz
mlba/csvFiles/ToyotaCorolla-original.csv.gz
mlba/csvFiles/ToyotaCorolla.csv.gz
mlba/csvFiles/ToysRUsRevenues.csv.gz
mlba/csvFiles/UniversalBank.csv.gz
mlba-2.0.2.dist-info/LICENSE
mlba-2.0.2.dist-info/METADATA
mlba-2.0.2.dist-info/WHEEL
mlba-2.0.2.dist-info/top_level.txt
mlba-2.0.2.dist-info/RECORD
