Metadata-Version: 2.1
Name: mlba
Version: 2.0.2
Summary: Utility functions for 'Machine Learning for Business Analytics: Concepts, Techniques, and Applications in Python' (2nd edition)
Home-page: https://github.com/gedeck/mlba-python
Author: Peter Gedeck
Author-email: mail@petergedeck.com
Classifier: Programming Language :: Python :: 3.10
Classifier: Programming Language :: Python :: 3.11
Classifier: Programming Language :: Python :: 3.12
Classifier: Programming Language :: Python :: 3.13
Classifier: License :: OSI Approved :: MIT License
Classifier: Operating System :: OS Independent
License-File: LICENSE
